{
  "py/object": "backend.data_containers.JsonObjectNode",
  "content": {
    "py/object": "backend.data_containers.BookPortion",
    "path": "local/hindi/scanned-misc"
  },
  "children": [
    {
      "py/object": "backend.data_containers.JsonObjectNode",
      "content": {
        "py/object": "backend.data_containers.BookPortion",
        "path": "local/hindi/scanned-misc/abhyAsEkChandaPuLa.jpg",
        "title": "pg_0",
        "targets": [],
        "authors": []
      },
      "children": []
    },
    {
      "py/object": "backend.data_containers.JsonObjectNode",
      "content": {
        "py/object": "backend.data_containers.BookPortion",
        "path": "local/hindi/scanned-misc/aksharunicodetext.jpg",
        "title": "pg_1",
        "targets": [],
        "authors": []
      },
      "children": []
    },
    {
      "py/object": "backend.data_containers.JsonObjectNode",
      "content": {
        "py/object": "backend.data_containers.BookPortion",
        "path": "local/hindi/scanned-misc/durga.jpg",
        "title": "pg_2",
        "targets": [],
        "authors": []
      },
      "children": []
    },
    {
      "py/object": "backend.data_containers.JsonObjectNode",
      "content": {
        "py/object": "backend.data_containers.BookPortion",
        "path": "local/hindi/scanned-misc/hi.png",
        "title": "pg_3",
        "targets": [],
        "authors": []
      },
      "children": []
    },
    {
      "py/object": "backend.data_containers.JsonObjectNode",
      "content": {
        "py/object": "backend.data_containers.BookPortion",
        "path": "local/hindi/scanned-misc/vishnu-chalisa.jpg",
        "title": "pg_4",
        "targets": [],
        "authors": []
      },
      "children": []
    }
  ]
}